LICENSE.txt
MANIFEST.in
README.rst
setup.py
klab/MultiWorker.py
klab/Reporter.py
klab/RosettaProtocols.py
klab/__init__.py
klab/box_backup.py
klab/chainsequence.py
klab/colortext.py
klab/constants.py
klab/docopt.py
klab/git.py
klab/klfilesystem.py
klab/latex.py
klab/mainpagehtml.py
klab/process.py
klab/process3.py
klab/retrospect.py
klab/scoretype.py
klab/scripting.py
klab/view_commit_log.py
klab.egg-info/PKG-INFO
klab.egg-info/SOURCES.txt
klab.egg-info/dependency_links.txt
klab.egg-info/entry_points.txt
klab.egg-info/top_level.txt
klab/benchmarking/__init__.py
klab/benchmarking/analysis/__init__.py
klab/benchmarking/analysis/ddg_binding_affinity_analysis.py
klab/benchmarking/analysis/ddg_monomeric_stability_analysis.py
klab/benchmarking/analysis/plot.py
klab/benchmarking/analysis/ssm.py
klab/biblio/__init__.py
klab/biblio/doi.py
klab/biblio/publication.py
klab/biblio/pubmed.py
klab/biblio/ris.py
klab/biblio/test.py
klab/bio/__init__.py
klab/bio/alignment.py
klab/bio/basics.py
klab/bio/blast.py
klab/bio/bonsai.py
klab/bio/cache.py
klab/bio/clustalo.py
klab/bio/complexes.py
klab/bio/dssp.py
klab/bio/fasta.py
klab/bio/kabsch.py
klab/bio/ligand.py
klab/bio/openbabel_util.py
klab/bio/pdb.py
klab/bio/pdb_util.py
klab/bio/pdbechem.py
klab/bio/pdbml.py
klab/bio/pdbtm.py
klab/bio/pfam.py
klab/bio/protein_sequence.py
klab/bio/rcsb.py
klab/bio/relatrix.py
klab/bio/renumber_pdb.py
klab/bio/scop.py
klab/bio/sifts.py
klab/bio/smallmolecule.py
klab/bio/spackle.py
klab/bio/subs_matrix.py
klab/bio/test.py
klab/bio/uniprot.py
klab/bio/uniprot_patches.py
klab/bio/units.py
klab/bio/xml_pdb_util.py
klab/bio/fragments/__init__.py
klab/bio/fragments/generate_fragments.py
klab/bio/fragments/make_fragments_QB3_cluster.pl
klab/bio/fragments/post_processing.py
klab/bio/fragments/utils.py
klab/bio/fragments/hpc/ClusterTask.py
klab/bio/fragments/hpc/SGE.py
klab/bio/fragments/hpc/__init__.py
klab/bio/pymolmod/__init__.py
klab/bio/pymolmod/colors.py
klab/bio/pymolmod/loop_removal.py
klab/bio/pymolmod/multi_structure_builder.py
klab/bio/pymolmod/psebuilder.py
klab/bio/pymolmod/scaffold_model_design.py
