Metadata-Version: 1.1
Name: klab
Version: 0.4.1
Summary: A collection of utilities used by our lab for computational biophysics
Home-page: https://github.com/Kortemme-Lab/klab
Author: Kortemme Lab, UCSF
Author-email: support@kortemmelab.ucsf.edu
License: MIT
Download-URL: https://github.com/Kortemme-Lab/klab/tarball/0.4.1
Keywords: utilities,library,biophysics
Platform: UNKNOWN
Classifier: Intended Audience :: Science/Research
Classifier: Topic :: Scientific/Engineering :: Bio-Informatics
Classifier: Development Status :: 3 - Alpha
Classifier: Programming Language :: Python :: 2
